{"cast":[{"adult":false,"gender":0,"id":2923256,"known_for_department":"Acting","name":"Sjoerd van Ramshorst","original_name":"Sjoerd van Ramshorst","popularity":1.115,"profile_path":"/7WkoEIWvhH8oilzb3Z6eEaBIeFm.jpg","character":"","credit_id":"60c311cc9369a20029119637","order":1},{"adult":false,"gender":2,"id":76251,"known_for_department":"Acting","name":"Herman Brusselmans","original_name":"Herman Brusselmans","popularity":2.603,"profile_path":"/AcpXBosNr7cCbRITng0FFjDXRzy.jpg","character":"","credit_id":"6671e8c4bcabf73e842a3846","order":4}],"crew":[],"id":126433}