{"id":42705,"page":1,"results":[{"description":"","favorite_count":0,"id":8270059,"item_count":10,"iso_639_1":"en","iso_3166_1":"US","name":"P10","poster_path":null},{"description":"Reyujays Tagalog List\r\nMovies and TV Series Tagalog Collection","favorite_count":0,"id":8302682,"item_count":790,"iso_639_1":"en","iso_3166_1":"US","name":"Reyujays Tagalog List","poster_path":null},{"description":"","favorite_count":0,"id":6927344,"item_count":695,"iso_639_1":"en","iso_3166_1":"US","name":"Top Rated Series (minimum 100 votes) - IMDb","poster_path":null},{"description":"","favorite_count":0,"id":6927356,"item_count":900,"iso_639_1":"en","iso_3166_1":"US","name":"Top Rated Series (minimum 1000 votes) - IMDb","poster_path":null},{"description":"GwaGwa Church Official TV Show Backlog.","favorite_count":0,"id":8254718,"item_count":113,"iso_639_1":"en","iso_3166_1":"US","name":"TV Backlog","poster_path":null},{"description":"","favorite_count":0,"id":146567,"item_count":186,"iso_639_1":"en","iso_3166_1":"US","name":"Anime Series","poster_path":null},{"description":"","favorite_count":0,"id":6713104,"item_count":2301,"iso_639_1":"en","iso_3166_1":"US","name":"Top Animes - IMDb","poster_path":null},{"description":"Movies and shows that I would like to recommend to everyone. Some are my favs and some are too good that I cannot help but praise them.","favorite_count":0,"id":8246123,"item_count":121,"iso_639_1":"en","iso_3166_1":"US","name":"Movies and Shows that I recommend","poster_path":null},{"description":"Tagalog Collection","favorite_count":0,"id":8279635,"item_count":865,"iso_639_1":"en","iso_3166_1":"US","name":"Tagalog Collection","poster_path":null},{"description":"Anime is awesome.","favorite_count":0,"id":8213299,"item_count":622,"iso_639_1":"en","iso_3166_1":"US","name":"THAT Hidden Anime Treasure","poster_path":null},{"description":"","favorite_count":0,"id":84639,"item_count":139,"iso_639_1":"en","iso_3166_1":"US","name":"Watched Anime","poster_path":null},{"description":"","favorite_count":0,"id":8279523,"item_count":102,"iso_639_1":"en","iso_3166_1":"US","name":"Anime Series","poster_path":null},{"description":"","favorite_count":0,"id":8270090,"item_count":320,"iso_639_1":"en","iso_3166_1":"US","name":"To Watch","poster_path":null},{"description":"Where you could watch whatever you want to watching likewise mobile services to help you stay connected with your business partners with. ","favorite_count":0,"id":8272772,"item_count":41,"iso_639_1":"en","iso_3166_1":"US","name":"All Movies Starts","poster_path":null},{"description":"","favorite_count":0,"id":7104246,"item_count":63,"iso_639_1":"en","iso_3166_1":"US","name":"Anime","poster_path":null},{"description":"TV Shows i would like to Watch","favorite_count":0,"id":32613,"item_count":321,"iso_639_1":"en","iso_3166_1":"US","name":"TV Watch List","poster_path":null},{"description":"","favorite_count":0,"id":8257210,"item_count":51,"iso_639_1":"en","iso_3166_1":"US","name":"TV 2000 (Anime)","poster_path":null},{"description":"","favorite_count":0,"id":8231194,"item_count":81,"iso_639_1":"en","iso_3166_1":"US","name":"anime 2000s","poster_path":null},{"description":"","favorite_count":0,"id":8243226,"item_count":1,"iso_639_1":"en","iso_3166_1":"US","name":"Test","poster_path":null},{"description":"","favorite_count":0,"id":6688384,"item_count":924,"iso_639_1":"en","iso_3166_1":"US","name":"Top Sports Titles - IMDb","poster_path":null}],"total_pages":2,"total_results":29}